statLM/__init__.py
statLM/ngram.py
statLM/statistical_models.py
tests/__init__.py
tests/context.py
tests/test.py
tests/test_models.py
statLM-0.0.2.dist-info/LICENSE.txt
statLM-0.0.2.dist-info/METADATA
statLM-0.0.2.dist-info/WHEEL
statLM-0.0.2.dist-info/top_level.txt
statLM-0.0.2.dist-info/RECORD
