Metadata-Version: 2.1
Name: statLM
Version: 0.0.2
Summary: Language models to predict words
Home-page: https://github.com/RaRedmer/statLM
Author: Raphael Redmer
Author-email: ra.redmer@outlook.com
License: MIT
Platform: UNKNOWN
Classifier: Programming Language :: Python :: 3
Classifier: License :: OSI Approved :: MIT License
Classifier: Operating System :: OS Independent
Requires-Python: >=3.7
Requires-Dist: nose
Requires-Dist: sphinx
Requires-Dist: sklearn
